ppdpy/__init__.py
ppdpy/exceptions.py
ppdpy/expression_compiler.py
ppdpy/nodes.py
ppdpy/template_compiler.py
ppdpy/utility.py
ppdpy/tests/__init__.py
ppdpy/tests/test_expression_compiler.py
ppdpy/tests/test_template_compiler.py
ppdpy/tests/test_utility.py
ppdpy-0.0.1.dist-info/LICENCE
ppdpy-0.0.1.dist-info/METADATA
ppdpy-0.0.1.dist-info/WHEEL
ppdpy-0.0.1.dist-info/top_level.txt
ppdpy-0.0.1.dist-info/RECORD
