Metadata-Version: 2.1
Name: ppdpy
Version: 0.0.1
Summary: Minimal templating using preprocessor directives
Home-page: https://github.com/ericvoid/ppdpy
Author: Eric J. Kinoshita
Author-email: eric.void@gmail.com
License: UNKNOWN
Platform: UNKNOWN
Classifier: Programming Language :: Python :: 3
Classifier: License :: OSI Approved :: MIT License
Classifier: Operating System :: OS Independent
Requires-Python: >=3.6
